forgeserve/__init__.py
forgeserve/__main__.py
forgeserve/_version.py
forgeserve/adapters/__init__.py
forgeserve/adapters/base.py
forgeserve/adapters/ollama.py
forgeserve/adapters/vllm.py
forgeserve/cli/__init__.py
forgeserve/cli/delete.py
forgeserve/cli/launch.py
forgeserve/cli/list_deployments.py
forgeserve/cli/logs.py
forgeserve/cli/main.py
forgeserve/cli/status.py
forgeserve/cli/utils.py
forgeserve/config/__init__.py
forgeserve/config/loaders.py
forgeserve/config/models.py
forgeserve/config/validation.py
forgeserve/core/__init__.py
forgeserve/core/deployment_manager.py
forgeserve/core/resource_generator.py
forgeserve/core/status_manager.py
forgeserve/runners/__init__.py
forgeserve/runners/base.py
forgeserve/runners/kubernetes.py
forgeserve/sdk/__init__.py
forgeserve/sdk/client.py
forgeserve/sdk/exceptions.py
forgeserve/templates/deployment.yaml.j2
forgeserve/templates/service.yaml.j2
forgeserve/utils/__init__.py
forgeserve/utils/common.py
forgeserve/utils/k8s_helpers.py
forgeserve/utils/yaml_utils.py
forgeserve-0.0.1.dist-info/METADATA
forgeserve-0.0.1.dist-info/WHEEL
forgeserve-0.0.1.dist-info/entry_points.txt
forgeserve-0.0.1.dist-info/licenses/LICENSE
forgeserve-0.0.1.dist-info/RECORD
