Metadata-Version: 2.4
Name: forgeserve
Version: 0.0.1
Summary: Declarative Deployment & Management for LLM Serving Frameworks (vLLM, TGI, Ollama, etc.) on Kubernetes.
Project-URL: Homepage, https://github.com/vonhatnam1212/ForgeServe
Project-URL: Repository, https://github.com/vonhatnam1212/ForgeServe
Author-email: Nhat Nam <vonhatnam.work@gmail.com>
License: Apache-2.0
License-File: LICENSE
Keywords: cli,deployment,inference,kubernetes,llm,mlops,ollama,sdk,tgi,vllm
Classifier: Development Status :: 3 - Alpha
Classifier: Intended Audience :: Developers
Classifier: Intended Audience :: Science/Research
Classifier: Intended Audience :: System Administrators
Classifier: License :: OSI Approved :: Apache Software License
Classifier: Operating System :: OS Independent
Classifier: Programming Language :: Python
Classifier: Programming Language :: Python :: 3
Classifier: Programming Language :: Python :: 3.8
Classifier: Programming Language :: Python :: 3.9
Classifier: Programming Language :: Python :: 3.10
Classifier: Programming Language :: Python :: 3.11
Classifier: Programming Language :: Python :: 3.12
Classifier: Topic :: Scientific/Engineering :: Artificial Intelligence
Classifier: Topic :: Software Development :: Libraries :: Python Modules
Classifier: Topic :: System :: Systems Administration
Classifier: Topic :: Utilities
Requires-Python: >=3.10
Requires-Dist: jinja2==3.1.6
Requires-Dist: kubernetes==32.0.1
Requires-Dist: pydantic==2.11.3
Requires-Dist: pyyaml==6.0.2
Requires-Dist: rich==14.0.0
Requires-Dist: typer==0.15.2
